actinia_metadata_plugin/__init__.py
actinia_metadata_plugin/endpoints.py
actinia_metadata_plugin/main.py
actinia_metadata_plugin/wsgi.py
actinia_metadata_plugin/api/__init__.py
actinia_metadata_plugin/api/common.py
actinia_metadata_plugin/api/files.py
actinia_metadata_plugin/api/metadata.py
actinia_metadata_plugin/apidocs/__init__.py
actinia_metadata_plugin/apidocs/files.py
actinia_metadata_plugin/apidocs/metadata.py
actinia_metadata_plugin/apidocs/examples/gnos_rawCategory_get_example.json
actinia_metadata_plugin/apidocs/examples/gnos_rawTags_get_example.json
actinia_metadata_plugin/apidocs/examples/gnos_rawUuid_get_example.json
actinia_metadata_plugin/core/__init__.py
actinia_metadata_plugin/core/common.py
actinia_metadata_plugin/core/gnosParser.py
actinia_metadata_plugin/core/gnosReader.py
actinia_metadata_plugin/core/gnosWriter.py
actinia_metadata_plugin/model/__init__.py
actinia_metadata_plugin/model/geodata.py
actinia_metadata_plugin/model/responseModels.py
actinia_metadata_plugin/resources/__init__.py
actinia_metadata_plugin/resources/config.py
actinia_metadata_plugin/resources/logging.py
actinia_metadata_plugin/resources/templating.py
actinia_metadata_plugin/static/index.html
actinia_metadata_plugin/static/javascripts/spectacle.min.js
actinia_metadata_plugin/static/stylesheets/actinia.css
actinia_metadata_plugin/static/stylesheets/foundation.min.css
actinia_metadata_plugin/static/stylesheets/spectacle.min.css
actinia_metadata_plugin/templates/README.md
actinia_metadata_plugin/templates/__init__.py
actinia_metadata_plugin/templates/geonetwork/get_record_by_uuid.json
actinia_metadata_plugin/templates/geonetwork/get_records_by_category_kvp.json
actinia_metadata_plugin/templates/geonetwork/post_create_record.xml
actinia_metadata_plugin/templates/geonetwork/post_records_by_tags.xml
actinia_metadata_plugin/templates/geonetwork/post_records_by_tags_outputschema_csw.xml
actinia_metadata_plugin/templates/geonetwork/post_records_by_tags_outputschema_gmd.xml
actinia_metadata_plugin-1.0.4.dist-info/licenses/LICENSE.txt
actinia_metadata_plugin-1.0.4.dist-info/METADATA
actinia_metadata_plugin-1.0.4.dist-info/WHEEL
actinia_metadata_plugin-1.0.4.dist-info/top_level.txt
actinia_metadata_plugin-1.0.4.dist-info/RECORD
